{
  "question_id": "hmvdx24003",
  "category": "hm",
  "educational_objective": "Diagnose chronic myeloid leukemia.",
  "metadata": {
    "care_types": [],
    "patient_types": [],
    "high_value_care": false,
    "question_updated": "12/27/2025"
  },
  "question_text": "A 60-year-old woman is evaluated after a leukocyte count of 55,000/µL (55 × 109/L) was found incidentally on a routine complete blood count.Peripheral blood smear is shown.",
  "question_stem": "Which of the following is the most likely diagnosis?",
  "options": [
    {
      "letter": "A",
      "text": "Acute lymphocytic leukemia",
      "peer_percentage": 0
    },
    {
      "letter": "B",
      "text": "Acute myeloid leukemia",
      "peer_percentage": 0
    },
    {
      "letter": "C",
      "text": "Chronic lymphocytic leukemia",
      "peer_percentage": 0
    },
    {
      "letter": "D",
      "text": "Chronic myeloid leukemia",
      "peer_percentage": 0
    }
  ],
  "user_performance": {
    "user_answer": null,
    "correct_answer": "D",
    "result": null,
    "time_taken": null
  },
  "critique": "The most likely diagnosis is chronic myeloid leukemia (CML) (Option D). CML is a clonal hematopoietic stem cell disorder characterized by translocation of the long arm of chromosomes 9 and 22 [t(9;22), Philadelphia chromosome] leading to a BCR::ABL fusion gene. This gene codes for an abnormal activated tyrosine kinase that promotes dysregulated cell proliferation. In CML, peripheral blood neutrophilia along with circulating immature myeloid forms, such as myelocytes and metamyelocytes, are seen. This peripheral blood smear shows myelocytes (red arrows), band forms (white arrows), and mature polymorphonuclear neutrophils (green arrows). At diagnosis, patients with CML can be asymptomatic, with elevated neutrophil counts found on routine laboratory studies, or they can have symptoms such as fatigue, weight loss, abdominal fullness (secondary to splenomegaly), and bleeding.",
  "critique_links": [],
  "key_points": [],
  "references": "",
  "related_content": {
    "syllabus": [
      "hmsec24002_24008"
    ],
    "learning_plan_topic": ""
  },
  "media": {
    "tables": [],
    "images": [
      "figures/hmfig24603.8d06c61788ea3d5a72234bf79ad937be.jpg",
      "figures/hmfig24604.3985f49b5ece8d96209ba355a9b52cac.jpg"
    ],
    "svgs": [],
    "videos": []
  },
  "media_metadata": {
    "figures": [
      {
        "figure_id": "hmfig24603",
        "file": "figures/hmfig24603.8d06c61788ea3d5a72234bf79ad937be.jpg",
        "title": "Stem Peripheral Blood Smear With Findings of Chronic Myeloid Leukemia",
        "short_title": "PBS in Chronic Myeloid Leukemia Stem",
        "number": null,
        "footnotes": [],
        "extension": "jpg",
        "width": 900,
        "height": 675
      },
      {
        "figure_id": "hmfig24604",
        "file": "figures/hmfig24604.3985f49b5ece8d96209ba355a9b52cac.jpg",
        "title": "Critique Peripheral Blood Smear With Findings of Chronic Myeloid Leukemia",
        "short_title": "PBS in Chronic Myeloid Leukemia Critique",
        "number": null,
        "footnotes": [],
        "extension": "jpg",
        "width": 900,
        "height": 675
      }
    ],
    "tables": [],
    "videos": [],
    "svgs": []
  },
  "extracted_at": "2025-12-27T00:29:29.083171-06:00"
}