{
  "question_id": "onvdx24003",
  "category": "on",
  "educational_objective": "Diagnose metastatic cancer spinal cord compression.",
  "metadata": {
    "care_types": [],
    "patient_types": [],
    "high_value_care": false,
    "question_updated": "12/27/2025"
  },
  "question_text": "A 54-year-old man is evaluated for back pain and bilateral leg weakness.An MRI of the spine is shown.",
  "question_stem": "Which of the following is the most likely diagnosis?",
  "options": [
    {
      "letter": "A",
      "text": "Diffuse idiopathic skeletal hyperostosis",
      "peer_percentage": 0
    },
    {
      "letter": "B",
      "text": "Herniated intervertebral disk",
      "peer_percentage": 0
    },
    {
      "letter": "C",
      "text": "Metastatic cancer spinal cord compression",
      "peer_percentage": 0
    },
    {
      "letter": "D",
      "text": "Spinal stenosis",
      "peer_percentage": 0
    }
  ],
  "user_performance": {
    "user_answer": null,
    "correct_answer": "C",
    "result": null,
    "time_taken": null
  },
  "critique": "The most likely diagnosis is spinal cord compression caused by metastatic cancer (Option C). The MRI of the spine shows metastatic cancer with collapse of the vertebral body and compression of the spinal cord from the posteriorly displaced bony fragments (arrow). High-dose systemic glucocorticoids should be administered immediately, and emergent neurosurgical consultation is indicated.",
  "critique_links": [],
  "key_points": [],
  "references": "",
  "related_content": {
    "syllabus": [
      "onsec24012_24006"
    ],
    "learning_plan_topic": ""
  },
  "media": {
    "tables": [],
    "images": [
      "figures/onfig24603.c2cf9fb88fa17d3a2e97a1af59c2b3c0.jpg",
      "figures/onfig24604.ef4345ea55e19cf9300f293cc142c9f8.jpg"
    ],
    "svgs": [],
    "videos": []
  },
  "media_metadata": {
    "figures": [
      {
        "figure_id": "onfig24603",
        "file": "figures/onfig24603.c2cf9fb88fa17d3a2e97a1af59c2b3c0.jpg",
        "title": "Spine MRI Showing Spinal Cord Compression",
        "short_title": "stem Spine MRI Showing Spinal Cord Compression",
        "number": null,
        "footnotes": [],
        "extension": "jpg",
        "width": 668,
        "height": 1065
      },
      {
        "figure_id": "onfig24604",
        "file": "figures/onfig24604.ef4345ea55e19cf9300f293cc142c9f8.jpg",
        "title": "Spine MRI Showing Spinal Cord Compression With Arrow",
        "short_title": "critique Spine MRI Showing Spinal Cord Compression With Arrow",
        "number": null,
        "footnotes": [],
        "extension": "jpg",
        "width": 668,
        "height": 1065
      }
    ],
    "tables": [],
    "videos": [],
    "svgs": []
  },
  "extracted_at": "2025-12-27T00:29:31.893935-06:00"
}