{
  "question_id": "pmvdx24013",
  "category": "pm",
  "category_name": "Pulmonary Medicine",
  "educational_objective": "Diagnose left mainstem bronchus obstruction.",
  "metadata": {
    "care_types": [],
    "patient_types": [],
    "high_value_care": false,
    "hospitalist": false,
    "question_updated": "01/01/2026"
  },
  "question_text": "A 79-year-old man is evaluated for cough and dyspnea. He has a 70-pack-year history of cigarette smoking.Chest radiographs are shown.",
  "question_stem": "Which of the following is the most likely diagnosis?",
  "options": [
    {
      "letter": "A",
      "text": "Left mainstem endobronchial obstruction",
      "peer_percentage": 0
    },
    {
      "letter": "B",
      "text": "Left pneumothorax",
      "peer_percentage": 0
    },
    {
      "letter": "C",
      "text": "Left upper lobe tuberculosis",
      "peer_percentage": 0
    },
    {
      "letter": "D",
      "text": "Right tension pneumothorax",
      "peer_percentage": 0
    }
  ],
  "user_performance": {
    "user_answer": null,
    "correct_answer": "A",
    "result": null,
    "time_taken": null
  },
  "critique": "The most likely diagnosis is left mainstem endobronchial obstruction (Option A), most likely caused by a tumor. The chest radiographs shown indicate the presence of left upper lobe atelectasis. An ill-defined opacification is seen at the left hilum and left upper lung field. The hilum has been displaced laterally and superiorly, the trachea is deviated to the left, and the left hemidiaphragm has been elevated because of the loss of volume in the left upper lobe. Note the absence of the normally visible lucency of the left mainstem bronchus (arrow, left panel), possibly indicating its obstruction (a potential cause of left upper lobe atelectasis). The lateral radiograph reveals the anterior displacement of the major fissure (arrows, right panel) and an opacification of the left upper lung field.",
  "critique_links": [],
  "key_points": [],
  "references": "",
  "related_content": {
    "syllabus": [
      "pmsec24007_24010"
    ]
  },
  "media": {
    "tables": [],
    "images": [
      "figures/pmfig24618.7ddea3f3622855e74e15a4d407fdd4cd.jpg",
      "figures/pmfig24619.a64d42571e55e4c87964448fb3147860.jpg",
      "figures/pmfig24620.18a788955479d654dd3d7e9e8d963c01.jpg"
    ],
    "svgs": [],
    "videos": []
  },
  "media_metadata": {
    "figures": [
      {
        "figure_id": "pmfig24618",
        "file": "figures/pmfig24618.7ddea3f3622855e74e15a4d407fdd4cd.jpg",
        "title": "Radiograph of Bronchus Obstruction",
        "short_title": "stem 1 Radiograph of Bronchus Obstruction",
        "number": null,
        "footnotes": [],
        "extension": "jpg",
        "width": 900,
        "height": 892
      },
      {
        "figure_id": "pmfig24619",
        "file": "figures/pmfig24619.a64d42571e55e4c87964448fb3147860.jpg",
        "title": "Radiograph of Bronchus Obstruction",
        "short_title": "stem 2 Radiograph of Bronchus Obstruction",
        "number": null,
        "footnotes": [],
        "extension": "jpg",
        "width": 900,
        "height": 1010
      },
      {
        "figure_id": "pmfig24620",
        "file": "figures/pmfig24620.18a788955479d654dd3d7e9e8d963c01.jpg",
        "title": "Radiograph of Bronchus Obstruction",
        "short_title": "critique Radiograph of Bronchus Obstruction",
        "number": null,
        "footnotes": [],
        "extension": "jpg",
        "width": 900,
        "height": 466
      }
    ],
    "tables": [],
    "videos": [],
    "svgs": []
  },
  "extracted_at": "2026-01-01T17:54:36.284407-06:00"
}