{
  "category": "id",
  "critique": "The most likely diagnosis is toxoplasmosis (Option D). In immunocompromised patients (e.g., in those with advanced HIV infection with a CD4 cell count <100/μL), latent infection may reactivate and result in Toxoplasma encephalitis, which typically presents with multiple brain lesions that localize in the parietal or frontal lobes, in the thalamus or basal ganglia, or at the corticomedullary junction. Ring enhancement of the brain lesions occurs in approximately 90% of patients, and surrounding edema with mass effect is also present, as seen in this image. Toxoplasma infection in immunocompetent patients is usually asymptomatic or may present with bilateral, symmetric, nontender cervical lymphadenopathy; latent infection is frequently lifelong.",
  "educational_objective": "Diagnose toxoplasmosis based on head CT findings.",
  "extracted_at": "2025-12-23T14:10:29.372262-06:00",
  "key_points": [],
  "media": {
    "images": [
      "figures/idfig24642.ef485fccf21ce7803fe297b74dcbfcbd.jpg"
    ],
    "svgs": [],
    "tables": [],
    "videos": []
  },
  "metadata": {
    "care_types": [],
    "high_value_care": false,
    "patient_types": [],
    "question_updated": "12/23/2025"
  },
  "options": [
    {
      "letter": "A",
      "peer_percentage": 0,
      "text": "Glioblastoma"
    },
    {
      "letter": "B",
      "peer_percentage": 0,
      "text": "Metastatic brain tumor"
    },
    {
      "letter": "C",
      "peer_percentage": 0,
      "text": "Progressive multifocal leukoencephalopathy"
    },
    {
      "letter": "D",
      "peer_percentage": 0,
      "text": "Toxoplasmosis"
    }
  ],
  "question_id": "idvdx24036",
  "question_stem": "Which of the following is the most likely diagnosis?",
  "question_text": "A 42-year-old woman who has HIV infection is evaluated for fever, confusion, and headache.A contrast-enhanced CT scan of the head is shown.",
  "references": "",
  "related_content": {
    "learning_plan_topic": "",
    "syllabus": [
      "idsec24019_24019"
    ]
  },
  "user_performance": {
    "correct_answer": "D",
    "result": null,
    "time_taken": null,
    "user_answer": null
  }
}