{
  "question_id": "idvdx24058",
  "category": "id",
  "category_name": "Infectious Disease",
  "educational_objective": "Diagnose Janeway lesions and recognize their association with infective endocarditis.",
  "metadata": {
    "care_types": [],
    "patient_types": [],
    "high_value_care": false,
    "hospitalist": false,
    "question_updated": "12/31/2025"
  },
  "question_text": "A 50-year-old man is evaluated for a 2-day history of fever and malaise. A new heart murmur is auscultated. Today, crops of nonpainful cutaneous lesions have appeared on his feet.",
  "question_stem": "Which of the following is the most likely diagnosis?",
  "options": [
    {
      "letter": "A",
      "text": "Anaplasmosis",
      "peer_percentage": 0
    },
    {
      "letter": "B",
      "text": "Atrial myxoma",
      "peer_percentage": 0
    },
    {
      "letter": "C",
      "text": "Infective endocarditis",
      "peer_percentage": 0
    },
    {
      "letter": "D",
      "text": "Secondary syphilis",
      "peer_percentage": 0
    }
  ],
  "user_performance": {
    "user_answer": null,
    "correct_answer": "C",
    "result": null,
    "time_taken": null
  },
  "critique": "The most likely diagnosis is infective endocarditis (Option C). This patient's skin findings are Janeway lesions, which are nonpainful, erythematous, macular lesions located on the palms and soles and caused by septic emboli. This cutaneous finding is associated with infective endocarditis.",
  "critique_links": [],
  "key_points": [],
  "references": "",
  "related_content": {
    "syllabus": [
      "idsec24005_24010"
    ],
    "learning_plan_topic": ""
  },
  "media": {
    "tables": [],
    "images": [],
    "svgs": [],
    "videos": []
  },
  "media_metadata": null,
  "extracted_at": "2025-12-31T17:07:55.714232-06:00"
}